pipeline/__init__.py
pipeline/unified_pipeline.py
todacomm/__init__.py
todacomm/cli.py
todacomm/analysis/__init__.py
todacomm/analysis/correlation.py
todacomm/analysis/dataset_comparison.py
todacomm/analysis/geometry.py
todacomm/analysis/interpretation.py
todacomm/analysis/meta_analysis.py
todacomm/data/__init__.py
todacomm/data/language_datasets.py
todacomm/data/standard_datasets.py
todacomm/extract/__init__.py
todacomm/extract/mlp_activations.py
todacomm/extract/transformer_activations.py
todacomm/models/__init__.py
todacomm/models/base.py
todacomm/models/mlp.py
todacomm/models/transformer.py
todacomm/tda/__init__.py
todacomm/tda/persistence.py
todacomm/training/__init__.py
todacomm/training/mlp_trainer.py
todacomm/utils/__init__.py
todacomm/visualization/__init__.py
todacomm/visualization/tda_plots.py
todacomm-0.1.0.dist-info/licenses/LICENSE
todacomm-0.1.0.dist-info/METADATA
todacomm-0.1.0.dist-info/WHEEL
todacomm-0.1.0.dist-info/entry_points.txt
todacomm-0.1.0.dist-info/top_level.txt
todacomm-0.1.0.dist-info/RECORD
