Metadata-Version: 2.4
Name: todacomm
Version: 0.1.0
Summary: ToDACoMM - Topological Data Analysis Comparison of Multiple Models
Author-email: Rajesh Sampathkumar <rexplorations@gmail.com>
License-Expression: MIT
Project-URL: Homepage, https://github.com/aiexplorations/todacomm
Project-URL: Repository, https://github.com/aiexplorations/todacomm
Project-URL: Issues, https://github.com/aiexplorations/todacomm/issues
Project-URL: Changelog, https://github.com/aiexplorations/todacomm/blob/main/CHANGELOG.md
Keywords: topological-data-analysis,persistent-homology,transformers,machine-learning,neural-networks
Classifier: Development Status :: 3 - Alpha
Classifier: Intended Audience :: Science/Research
Classifier: Operating System :: OS Independent
Classifier: Topic :: Scientific/Engineering :: Artificial Intelligence
Classifier: Topic :: Scientific/Engineering :: Mathematics
Classifier: Programming Language :: Python :: 3
Classifier: Programming Language :: Python :: 3.9
Classifier: Programming Language :: Python :: 3.10
Classifier: Programming Language :: Python :: 3.11
Classifier: Programming Language :: Python :: 3.12
Classifier: Programming Language :: Python :: 3.13
Requires-Python: >=3.9
License-File: LICENSE
Requires-Dist: numpy>=1.24.0
Requires-Dist: scipy>=1.10.0
Requires-Dist: pandas>=2.0.0
Requires-Dist: scikit-learn>=1.3.0
Requires-Dist: matplotlib>=3.7.0
Requires-Dist: seaborn>=0.12.0
Requires-Dist: torch>=2.0.0
Requires-Dist: torchvision>=0.15.0
Requires-Dist: transformers>=4.35.0
Requires-Dist: datasets>=2.14.0
Requires-Dist: tokenizers>=0.15.0
Requires-Dist: ripser>=0.6.4
Requires-Dist: persim>=0.3.1
Requires-Dist: pyyaml>=6.0
Requires-Dist: tqdm>=4.66.0
Provides-Extra: dev
Requires-Dist: pytest>=7.4.0; extra == "dev"
Requires-Dist: black>=23.0.0; extra == "dev"
Requires-Dist: isort>=5.12.0; extra == "dev"
Requires-Dist: jupyter>=1.0.0; extra == "dev"
Dynamic: license-file
